[
  {
    "id": "budget-plovdiv-2002-total",
    "year": 2002,
    "municipality": "plovdiv",
    "kind": "summary",
    "summary_key": "total_budget",
    "basis": "adopted",
    "category": "other",
    "title_bg": "Общ бюджет за 2002 г.",
    "title_en": "Total 2002 budget",
    "amount_bgn": 86100000,
    "currency": "BGN",
    "plain_language_bg": "Приет бюджет на Община Пловдив за 2002 г. - 86 100 000 лв., цитиран в одитния доклад на Сметната палата за изпълнението към 30.09.2002 г.",
    "plain_language_en": "Adopted Plovdiv Municipality budget for 2002 - BGN 86,100,000, cited in the National Audit Office report on execution as of 30.09.2002.",
    "source_document": {
      "title": "Сметна палата - финансов одит на бюджета на Община Пловдив към 30.09.2002 г.",
      "url": "https://www.bulnao.government.bg/media/documents/doklad_Pv.doc",
      "accessed_at": "2026-06-17"
    },
    "data_quality": "manual_reviewed",
    "title_de": "Gesamthaushalt 2002",
    "title_fr": "Budget total 2002",
    "title_it": "Bilancio totale 2002",
    "title_tr": "Toplam 2002 bütçesi",
    "title_es": "Presupuesto total para 2002",
    "plain_language_de": "Verabschiedeter Haushaltsplan der Gemeinde Plovdiv für 2002 – 86.100.000 BGN, zitiert im Bericht des Nationalen Rechnungshofs über die Ausführung vom 30.09.2002.",
    "plain_language_fr": "Budget de la municipalité de Plovdiv adopté pour 2002 - 86 100 000 BGN, cité dans le rapport du Bureau national d'audit sur l'exécution du 30 septembre 2002.",
    "plain_language_it": "Bilancio adottato dal Comune di Plovdiv per il 2002 - 86.100.000 BGN, citato nel rapporto di esecuzione dell'Ufficio nazionale di revisione contabile del 30.09.2002.",
    "plain_language_tr": "2002 yılı için kabul edilen Plovdiv Belediyesi bütçesi - 86.100.000 BGN, Ulusal Denetleme Bürosu'nun 30.09.2002 tarihli uygulamaya ilişkin raporunda belirtilmiştir.",
    "plain_language_es": "Presupuesto adoptado por el municipio de Plovdiv para 2002: 86.100.000 BGN, citado en el informe de la Oficina Nacional de Auditoría sobre la ejecución al 30 de septiembre de 2002."
  },
  {
    "id": "budget-plovdiv-2002-capital-programme",
    "year": 2002,
    "municipality": "plovdiv",
    "kind": "summary",
    "summary_key": "capital_programme",
    "basis": "adopted",
    "category": "other",
    "title_bg": "Капиталови разходи за 2002 г.",
    "title_en": "2002 capital expenditure",
    "amount_bgn": 13125766,
    "currency": "BGN",
    "plain_language_bg": "Средствата за капиталови разходи през 2002 г. са определени в размер на 13 125 766 лв., според одитния доклад на Сметната палата.",
    "plain_language_en": "Capital expenditure for 2002 was set at BGN 13,125,766, according to the National Audit Office report.",
    "source_document": {
      "title": "Сметна палата - финансов одит на бюджета на Община Пловдив към 30.09.2002 г.",
      "url": "https://www.bulnao.government.bg/media/documents/doklad_Pv.doc",
      "accessed_at": "2026-06-17"
    },
    "data_quality": "manual_reviewed",
    "title_de": "Investitionen 2002",
    "title_fr": "Investissements 2002",
    "title_it": "Spese in conto capitale del 2002",
    "title_tr": "2002 sermaye harcaması",
    "title_es": "Gastos de capital de 2002",
    "plain_language_de": "Laut dem Bericht des National Audit Office wurden die Investitionsausgaben für 2002 auf 13.125.766 BGN veranschlagt.",
    "plain_language_fr": "Les dépenses en capital pour 2002 ont été fixées à 13 125 766 BGN, selon le rapport du Bureau national d'audit.",
    "plain_language_it": "Secondo il rapporto del National Audit Office, la spesa in conto capitale per il 2002 è stata fissata a 13.125.766 BGN.",
    "plain_language_tr": "Ulusal Denetim Ofisi raporuna göre 2002 yılı sermaye harcaması 13.125.766 BGN olarak belirlendi.",
    "plain_language_es": "Según el informe de la Oficina Nacional de Auditoría, los gastos de capital para 2002 se fijaron en 13.125.766 BGN."
  },
  {
    "id": "budget-plovdiv-2005-capital-execution",
    "year": 2005,
    "municipality": "plovdiv",
    "kind": "summary",
    "summary_key": "capital_programme",
    "basis": "executed",
    "category": "other",
    "title_bg": "Реализирани капиталови разходи за 2005 г.",
    "title_en": "Executed 2005 capital expenditure",
    "amount_bgn": 16988269,
    "currency": "BGN",
    "plain_language_bg": "Функционалният анализ на Общинска администрация Пловдив отчита реализирани капиталови разходи за 2005 г. в размер на 16 988 269 лв.",
    "plain_language_en": "The functional analysis of Plovdiv municipal administration reports executed 2005 capital expenditure of BGN 16,988,269.",
    "source_document": {
      "title": "Доклад за функционален анализ в Общинска администрация Пловдив, януари 2009 г.",
      "url": "https://www.strategy.bg/files/publications/%D0%94%D0%BE%D0%BA%D0%BB%D0%B0%D0%B4%20%D0%B7%D0%B0%20%D0%BF%D1%80%D0%BE%D0%B2%D0%B5%D0%B4%D0%B5%D0%BD%20%D1%84%D1%83%D0%BD%D0%BA%D1%86%D0%B8%D0%BE%D0%BD%D0%B0%D0%BB%D0%B5%D0%BD%20%D0%B0%D0%BD%D0%B0%D0%BB%D0%B8%D0%B7%20%D0%B2%20%D0%9E%D0%B1%D1%89%D0%B8%D0%BD%D1%81%D0%BA%D0%B0%20%D0%B0%D0%B4%D0%BC%D0%B8%D0%BD%D0%B8%D1%81%D1%82%D1%80%D0%B0%D1%86%D0%B8%D1%8F%20%D0%9F%D0%BB%D0%BE%D0%B2%D0%B4%D0%B8%D0%B2.pdf",
      "accessed_at": "2026-06-17"
    },
    "data_quality": "manual_reviewed",
    "title_de": "Investitionsausgabe 2005 durchgeführt",
    "title_fr": "Investissements réalisés en 2005",
    "title_it": "Spese in conto capitale eseguite nel 2005",
    "title_tr": "2005 yılı sermaye harcaması gerçekleştirildi",
    "title_es": "Gastos de capital ejecutados en 2005",
    "plain_language_de": "Die Funktionsanalyse der Berichte der Stadtverwaltung von Plovdiv ergab für 2005 Investitionsausgaben in Höhe von 16.988.269 BGN.",
    "plain_language_fr": "L'analyse fonctionnelle des rapports de l'administration municipale de Plovdiv a réalisé des dépenses en capital de 2005 d'un montant de 16 988 269 BGN.",
    "plain_language_it": "L'analisi funzionale dei rapporti dell'amministrazione comunale di Plovdiv ha eseguito nel 2005 una spesa in conto capitale di 16.988.269 BGN.",
    "plain_language_tr": "Plovdiv belediye yönetim raporlarının işlevsel analizi, 2005 yılında 16.988.269 BGN'lik sermaye harcamasını ortaya çıkardı.",
    "plain_language_es": "Según el análisis funcional de los informes de la administración municipal de Plovdiv, en 2005 los gastos de capital ascendieron a 16.988.269 BGN."
  },
  {
    "id": "budget-plovdiv-2006-capital-execution",
    "year": 2006,
    "municipality": "plovdiv",
    "kind": "summary",
    "summary_key": "capital_programme",
    "basis": "executed",
    "category": "other",
    "title_bg": "Реализирани капиталови разходи за 2006 г.",
    "title_en": "Executed 2006 capital expenditure",
    "amount_bgn": 26898140,
    "currency": "BGN",
    "plain_language_bg": "Функционалният анализ на Общинска администрация Пловдив отчита реализирани капиталови разходи за 2006 г. в размер на 26 898 140 лв.",
    "plain_language_en": "The functional analysis of Plovdiv municipal administration reports executed 2006 capital expenditure of BGN 26,898,140.",
    "source_document": {
      "title": "Доклад за функционален анализ в Общинска администрация Пловдив, януари 2009 г.",
      "url": "https://www.strategy.bg/files/publications/%D0%94%D0%BE%D0%BA%D0%BB%D0%B0%D0%B4%20%D0%B7%D0%B0%20%D0%BF%D1%80%D0%BE%D0%B2%D0%B5%D0%B4%D0%B5%D0%BD%20%D1%84%D1%83%D0%BD%D0%BA%D1%86%D0%B8%D0%BE%D0%BD%D0%B0%D0%BB%D0%B5%D0%BD%20%D0%B0%D0%BD%D0%B0%D0%BB%D0%B8%D0%B7%20%D0%B2%20%D0%9E%D0%B1%D1%89%D0%B8%D0%BD%D1%81%D0%BA%D0%B0%20%D0%B0%D0%B4%D0%BC%D0%B8%D0%BD%D0%B8%D1%81%D1%82%D1%80%D0%B0%D1%86%D0%B8%D1%8F%20%D0%9F%D0%BB%D0%BE%D0%B2%D0%B4%D0%B8%D0%B2.pdf",
      "accessed_at": "2026-06-17"
    },
    "data_quality": "manual_reviewed",
    "title_de": "Investitionsausgabe 2006 durchgeführt",
    "title_fr": "Investissements réalisés en 2006",
    "title_it": "Spese in conto capitale eseguite nel 2006",
    "title_tr": "2006 yılı sermaye harcaması gerçekleştirildi",
    "title_es": "Gastos de capital ejecutados en 2006",
    "plain_language_de": "Die Funktionsanalyse der Berichte der Stadtverwaltung von Plovdiv ergab für 2006 Investitionsausgaben in Höhe von 26.898.140 BGN.",
    "plain_language_fr": "L'analyse fonctionnelle des rapports de l'administration municipale de Plovdiv a réalisé des dépenses en capital de 26 898 140 BGN en 2006.",
    "plain_language_it": "L'analisi funzionale dei rapporti dell'amministrazione comunale di Plovdiv ha eseguito nel 2006 una spesa in conto capitale di 26.898.140 BGN.",
    "plain_language_tr": "Plovdiv belediye yönetim raporlarının işlevsel analizi, 2006 yılında 26.898.140 BGN'lik sermaye harcamasını ortaya çıkardı.",
    "plain_language_es": "Según el análisis funcional de los informes de la administración municipal de Plovdiv, en 2006 los gastos de capital ascendieron a 26.898.140 BGN."
  },
  {
    "id": "budget-plovdiv-2007-capital-execution",
    "year": 2007,
    "municipality": "plovdiv",
    "kind": "summary",
    "summary_key": "capital_programme",
    "basis": "executed",
    "category": "other",
    "title_bg": "Реализирани капиталови разходи за 2007 г.",
    "title_en": "Executed 2007 capital expenditure",
    "amount_bgn": 50858123,
    "currency": "BGN",
    "plain_language_bg": "Функционалният анализ на Общинска администрация Пловдив отчита реализирани капиталови разходи за 2007 г. в размер на 50 858 123 лв.",
    "plain_language_en": "The functional analysis of Plovdiv municipal administration reports executed 2007 capital expenditure of BGN 50,858,123.",
    "source_document": {
      "title": "Доклад за функционален анализ в Общинска администрация Пловдив, януари 2009 г.",
      "url": "https://www.strategy.bg/files/publications/%D0%94%D0%BE%D0%BA%D0%BB%D0%B0%D0%B4%20%D0%B7%D0%B0%20%D0%BF%D1%80%D0%BE%D0%B2%D0%B5%D0%B4%D0%B5%D0%BD%20%D1%84%D1%83%D0%BD%D0%BA%D1%86%D0%B8%D0%BE%D0%BD%D0%B0%D0%BB%D0%B5%D0%BD%20%D0%B0%D0%BD%D0%B0%D0%BB%D0%B8%D0%B7%20%D0%B2%20%D0%9E%D0%B1%D1%89%D0%B8%D0%BD%D1%81%D0%BA%D0%B0%20%D0%B0%D0%B4%D0%BC%D0%B8%D0%BD%D0%B8%D1%81%D1%82%D1%80%D0%B0%D1%86%D0%B8%D1%8F%20%D0%9F%D0%BB%D0%BE%D0%B2%D0%B4%D0%B8%D0%B2.pdf",
      "accessed_at": "2026-06-17"
    },
    "data_quality": "manual_reviewed",
    "title_de": "Investitionsausgabe 2007 durchgeführt",
    "title_fr": "Investissements réalisés en 2007",
    "title_it": "Spese in conto capitale eseguite nel 2007",
    "title_tr": "2007 yılında gerçekleştirilen sermaye harcaması",
    "title_es": "Gastos de capital ejecutados en 2007",
    "plain_language_de": "Die Funktionsanalyse der Berichte der Stadtverwaltung von Plovdiv ergab für 2007 Investitionsausgaben in Höhe von 50.858.123 BGN.",
    "plain_language_fr": "L'analyse fonctionnelle des rapports de l'administration municipale de Plovdiv a réalisé des dépenses en capital de 2007 d'un montant de 50 858 123 BGN.",
    "plain_language_it": "L'analisi funzionale dei rapporti dell'amministrazione comunale di Plovdiv ha eseguito nel 2007 una spesa in conto capitale di 50.858.123 BGN.",
    "plain_language_tr": "Plovdiv belediye yönetim raporlarının işlevsel analizi, 2007 yılında 50.858.123 BGN'lik sermaye harcamasını ortaya çıkardı.",
    "plain_language_es": "El análisis funcional de los informes de la administración municipal de Plovdiv ejecutó un gasto de capital de 50.858.123 BGN en 2007."
  },
  {
    "id": "budget-plovdiv-2008-draft-total",
    "year": 2008,
    "municipality": "plovdiv",
    "kind": "summary",
    "summary_key": "total_budget",
    "basis": "provisional",
    "category": "other",
    "title_bg": "Проектобюджет за 2008 г.",
    "title_en": "2008 draft budget",
    "amount_bgn": 218300000,
    "currency": "BGN",
    "plain_language_bg": "Съвременна публикация на gradat.bg описва предложението Пловдив да се управлява през 2008 г. с проектобюджет от 218,3 млн. лв. Това е проектна стойност, не открито официално решение за приет бюджет.",
    "plain_language_en": "A contemporary gradat.bg report describes a proposal for Plovdiv to operate in 2008 with a BGN 218.3M draft budget. This is a draft value, not a located official adopted-budget decision.",
    "source_document": {
      "title": "Градът - Община Пловдив с проектобюджет от 218.3 млн. лева",
      "url": "https://gradat.bg/news/2008/02/16/459862_obshtina_plovdiv_s_proektobjudjet_ot_2183_mln_leva",
      "accessed_at": "2026-06-17"
    },
    "data_quality": "public_source",
    "title_de": "Haushaltsentwurf 2008",
    "title_fr": "projet de budget 2008",
    "title_it": "Progetto di bilancio 2008",
    "title_tr": "2008 bütçe taslağı",
    "title_es": "proyecto de presupuesto 2008",
    "plain_language_de": "Ein zeitgenössischer Bericht von gradat.bg beschreibt einen Vorschlag, Plovdiv im Jahr 2008 mit einem Haushaltsentwurf von 218,3 Mio. BGN zu betreiben. Hierbei handelt es sich um einen Entwurfswert, nicht um einen amtlich verabschiedeten Haushaltsbeschluss.",
    "plain_language_fr": "Un rapport contemporain de gradat.bg décrit une proposition selon laquelle Plovdiv fonctionnerait en 2008 avec un projet de budget de 218,3 millions de BGN. Il s’agit d’un projet de valeur et non d’une décision budgétaire officielle adoptée.",
    "plain_language_it": "Un rapporto contemporaneo di gradat.bg descrive una proposta per Plovdiv di operare nel 2008 con un progetto di budget di 218,3 milioni di BGN. Si tratta di una bozza di valore, non di una decisione ufficiale di bilancio adottato.",
    "plain_language_tr": "Çağdaş bir gradat.bg raporu, Plovdiv'in 2008 yılında 218,3 milyon BGN'lik bir taslak bütçeyle faaliyet göstermesine yönelik bir öneriyi açıklıyor. Bu bir taslak değerdir, resmi olarak kabul edilmiş bir bütçe kararı değildir.",
    "plain_language_es": "Un informe contemporáneo de gradat.bg describe una propuesta para que Plovdiv funcione en 2008 con un proyecto de presupuesto de 218,3 millones de BGN. Este es un valor preliminar, no una decisión presupuestaria oficial adoptada localizada."
  },
  {
    "id": "budget-plovdiv-2008-draft-capital-programme",
    "year": 2008,
    "municipality": "plovdiv",
    "kind": "summary",
    "summary_key": "capital_programme",
    "basis": "provisional",
    "category": "other",
    "title_bg": "Проектна капиталова програма за 2008 г.",
    "title_en": "2008 draft capital programme",
    "amount_bgn": 73064443,
    "currency": "BGN",
    "plain_language_bg": "В проектобюджета за 2008 г., описан от gradat.bg, за капиталови разходи са заложени 73 064 443 лв., или около 30% от общия проектобюджет.",
    "plain_language_en": "In the 2008 draft budget described by gradat.bg, BGN 73,064,443 was planned for capital expenditure, about 30% of the total draft budget.",
    "source_document": {
      "title": "Градът - Община Пловдив с проектобюджет от 218.3 млн. лева",
      "url": "https://gradat.bg/news/2008/02/16/459862_obshtina_plovdiv_s_proektobjudjet_ot_2183_mln_leva",
      "accessed_at": "2026-06-17"
    },
    "data_quality": "public_source",
    "title_de": "Entwurf des Kapitalprogramms 2008",
    "title_fr": "Projet de programme d'investissement 2008",
    "title_it": "Progetto di programma di capitale del 2008",
    "title_tr": "2008 taslak sermaye programı",
    "title_es": "Proyecto de programa de capital de 2008",
    "plain_language_de": "Im von gradat.bg beschriebenen Haushaltsentwurf 2008 waren 73.064.443 BGN für Investitionsausgaben vorgesehen, etwa 30 % des gesamten Haushaltsentwurfs.",
    "plain_language_fr": "Dans le projet de budget 2008 décrit par gradat.bg, 73 064 443 BGN étaient prévus pour les dépenses en capital, soit environ 30 % du projet de budget total.",
    "plain_language_it": "Nel progetto di bilancio del 2008 descritto da gradat.bg, erano previsti 73.064.443 BGN per le spese in conto capitale, circa il 30% del progetto di bilancio totale.",
    "plain_language_tr": "Gradat.bg tarafından açıklanan 2008 bütçe taslağında, toplam bütçe taslağının yaklaşık %30'una tekabül eden 73.064.443 BGN sermaye harcaması planlanmıştı.",
    "plain_language_es": "En el proyecto de presupuesto de 2008 descrito en gradat.bg, se previeron 73.064.443 BGN para gastos de capital, alrededor del 30% del proyecto de presupuesto total."
  },
  {
    "id": "budget-plovdiv-2009-total",
    "year": 2009,
    "municipality": "plovdiv",
    "kind": "summary",
    "summary_key": "total_budget",
    "basis": "adopted",
    "category": "other",
    "title_bg": "Общ бюджет за 2009 г.",
    "title_en": "Total 2009 budget",
    "amount_bgn": 260702383,
    "currency": "BGN",
    "plain_language_bg": "Приет бюджет на Община Пловдив за 2009 г. - 260 702 383 лв., цитиран от Plovdiv24.bg при гласуването на бюджета на 5 март 2009 г.",
    "plain_language_en": "Adopted Plovdiv Municipality budget for 2009 - BGN 260,702,383, cited by Plovdiv24.bg during the 5 March 2009 budget vote.",
    "source_document": {
      "title": "Plovdiv24.bg - Рекорден бюджет - 260 702 383 лева",
      "url": "https://www.plovdiv24.bg/novini/plovdiv/Rekorden-byudzhet-260-702-383-leva-79980",
      "accessed_at": "2026-06-17"
    },
    "data_quality": "public_source",
    "title_de": "Gesamthaushalt 2009",
    "title_fr": "Budget total 2009",
    "title_it": "Bilancio totale 2009",
    "title_tr": "Toplam 2009 bütçesi",
    "title_es": "Presupuesto total para 2009",
    "plain_language_de": "Verabschiedeter Haushaltsplan der Gemeinde Plovdiv für 2009 – 260.702.383 BGN, zitiert von Plovdiv24.bg bei der Haushaltsabstimmung am 5. März 2009.",
    "plain_language_fr": "Budget de la municipalité de Plovdiv adopté pour 2009 - 260 702 383 BGN, cité par Plovdiv24.bg lors du vote du budget du 5 mars 2009.",
    "plain_language_it": "Bilancio del Comune di Plovdiv adottato per il 2009 - 260.702.383 BGN, citato da Plovdiv24.bg durante la votazione sul bilancio del 5 marzo 2009.",
    "plain_language_tr": "2009 yılı Plovdiv Belediyesi bütçesi kabul edildi - 260.702.383 BGN, 5 Mart 2009 bütçe oylaması sırasında Plovdiv24.bg tarafından alıntılanmıştır.",
    "plain_language_es": "Presupuesto adoptado por el municipio de Plovdiv para 2009: 260.702.383 BGN, citado por Plovdiv24.bg durante la votación del presupuesto del 5 de marzo de 2009."
  },
  {
    "id": "budget-plovdiv-2009-capital-programme",
    "year": 2009,
    "municipality": "plovdiv",
    "kind": "summary",
    "summary_key": "capital_programme",
    "basis": "adopted",
    "category": "other",
    "title_bg": "Капиталови разходи за 2009 г.",
    "title_en": "2009 capital expenditure",
    "amount_bgn": 77000000,
    "currency": "BGN",
    "plain_language_bg": "При приемането на бюджета за 2009 г. Plovdiv24.bg съобщава, че за капиталови разходи и инфраструктура са отделени 77 млн. лв.",
    "plain_language_en": "When the 2009 budget was adopted, Plovdiv24.bg reported BGN 77M allocated for capital expenditure and infrastructure.",
    "source_document": {
      "title": "Plovdiv24.bg - Рекорден бюджет - 260 702 383 лева",
      "url": "https://www.plovdiv24.bg/novini/plovdiv/Rekorden-byudzhet-260-702-383-leva-79980",
      "accessed_at": "2026-06-17"
    },
    "data_quality": "public_source",
    "title_de": "Investitionen 2009",
    "title_fr": "Investissements 2009",
    "title_it": "Spese in conto capitale 2009",
    "title_tr": "2009 sermaye harcaması",
    "title_es": "Gastos de capital de 2009",
    "plain_language_de": "Als der Haushalt 2009 angenommen wurde, meldete Plovdiv24.bg, dass 77 Mio. BGN für Investitionsausgaben und Infrastruktur bereitgestellt wurden.",
    "plain_language_fr": "Lorsque le budget 2009 a été adopté, Plovdiv24.bg a annoncé que 77 millions de BGN étaient alloués aux dépenses en capital et aux infrastructures.",
    "plain_language_it": "Quando è stato adottato il bilancio del 2009, Plovdiv24.bg ha riportato che 77 milioni di BGN erano stati stanziati per spese in conto capitale e infrastrutture.",
    "plain_language_tr": "2009 bütçesi kabul edildiğinde Plovdiv24.bg, sermaye harcamaları ve altyapı için 77 milyon BGN tahsis edildiğini bildirdi.",
    "plain_language_es": "Cuando se adoptó el presupuesto de 2009, Plovdiv24.bg informó que se habían asignado 77 millones de BGN para gastos de capital e infraestructura."
  },
  {
    "id": "budget-plovdiv-2010-execution-total",
    "year": 2010,
    "municipality": "plovdiv",
    "kind": "summary",
    "summary_key": "budget_execution",
    "basis": "executed",
    "category": "other",
    "title_bg": "Изпълнение на сборния бюджет за 2010 г.",
    "title_en": "2010 consolidated budget execution",
    "amount_bgn": 212194674,
    "currency": "BGN",
    "plain_language_bg": "Отчет за изпълнение на сборния бюджет на Община Пловдив за 2010 г. - 212 194 674 лв. отчетени приходи/разходи към 31.12.2010 г.",
    "plain_language_en": "Execution report for Plovdiv Municipality consolidated 2010 budget - BGN 212,194,674 reported revenue/expenditure as of 31.12.2010.",
    "source_document": {
      "title": "Общински съвет - Пловдив, Решение №58 за отчет на бюджет 2010",
      "url": "https://plovdiv.bg/obs/%d0%b4%d0%b5%d0%b9%d1%81%d1%82%d0%b2%d0%b0%d1%89%d0%b8-%d0%b0%d0%ba%d1%82%d0%be%d0%b2%d0%b5/%d1%80%d0%b5%d1%88%d0%b5%d0%bd%d0%b8%d0%b5-58-1/",
      "accessed_at": "2026-06-17"
    },
    "data_quality": "manual_reviewed",
    "title_de": "Konsolidierter Haushaltsvollzug 2010",
    "title_fr": "Exécution du budget consolidé 2010",
    "title_it": "Esecuzione del bilancio consolidato 2010",
    "title_tr": "2010 konsolide bütçe uygulaması",
    "title_es": "Ejecución presupuestaria consolidada 2010",
    "plain_language_de": "Ausführungsbericht für den konsolidierten Haushalt 2010 der Gemeinde Plovdiv – ausgewiesene Einnahmen/Ausgaben in Höhe von 212.194.674 BGN zum 31.12.2010.",
    "plain_language_fr": "Rapport d'exécution du budget consolidé 2010 de la municipalité de Plovdiv - 212 194 674 BGN de recettes/dépenses déclarées au 31.12.2010.",
    "plain_language_it": "Rapporto di esecuzione per il bilancio consolidato 2010 del Comune di Plovdiv - 212.194.674 BGN, entrate/spese riportate al 31.12.2010.",
    "plain_language_tr": "Plovdiv Belediyesi'nin konsolide 2010 bütçesi için uygulama raporu - 31.12.2010 itibarıyla 212.194.674 BGN gelir/gider rapor edilmiştir.",
    "plain_language_es": "Informe de ejecución del presupuesto consolidado de 2010 del municipio de Plovdiv: 212.194.674 BGN declarados ingresos/gastos al 31 de diciembre de 2010."
  },
  {
    "id": "budget-plovdiv-2011-total",
    "year": 2011,
    "municipality": "plovdiv",
    "kind": "summary",
    "summary_key": "total_budget",
    "category": "other",
    "title_bg": "Общ бюджет за 2011 г.",
    "title_en": "Total 2011 budget",
    "amount_bgn": 189636285,
    "currency": "BGN",
    "plain_language_bg": "Приет бюджет на Община Пловдив за 2011 г. (189 636 285 лв.) според решение на Общински съвет - Пловдив.",
    "plain_language_en": "Adopted Plovdiv Municipality budget for 2011 (BGN 189,636,285), from a Plovdiv Municipal Council decision.",
    "source_document": {
      "title": "Общински съвет - Пловдив, Решение № 26 за бюджет 2011",
      "url": "https://plovdiv.bg/obs/%D0%B4%D0%B5%D0%B9%D1%81%D1%82%D0%B2%D0%B0%D1%89%D0%B8-%D0%B0%D0%BA%D1%82%D0%BE%D0%B2%D0%B5/%D1%80%D0%B5%D1%88%D0%B5%D0%BD%D0%B8%D0%B5-26-1/",
      "accessed_at": "2026-06-17"
    },
    "data_quality": "manual_reviewed",
    "title_de": "Gesamtbudget 2011",
    "title_fr": "Budget total 2011",
    "title_it": "Bilancio totale 2011",
    "title_tr": "Toplam 2011 bütçesi",
    "title_es": "Presupuesto total para 2011",
    "plain_language_de": "Verabschiedung des Haushaltsplans der Gemeinde Plovdiv für 2011 (189.636.285 BGN), basierend auf einem Beschluss des Gemeinderats von Plovdiv.",
    "plain_language_fr": "Adoption du budget de la municipalité de Plovdiv pour 2011 (189 636 285 BGN), sur décision du conseil municipal de Plovdiv.",
    "plain_language_it": "Adottato il bilancio del Comune di Plovdiv per il 2011 (189.636.285 BGN), in base a una decisione del Consiglio municipale di Plovdiv.",
    "plain_language_tr": "Plovdiv Belediye Meclisi kararından 2011 yılı Plovdiv Belediyesi bütçesi (189.636.285 BGN) kabul edildi.",
    "plain_language_es": "Se adoptó el presupuesto del municipio de Plovdiv para 2011 (189.636.285 BGN), a partir de una decisión del Consejo Municipal de Plovdiv."
  },
  {
    "id": "budget-plovdiv-2012-total",
    "year": 2012,
    "municipality": "plovdiv",
    "kind": "summary",
    "summary_key": "total_budget",
    "category": "other",
    "title_bg": "Общ бюджет за 2012 г.",
    "title_en": "Total 2012 budget",
    "amount_bgn": 193344980,
    "currency": "BGN",
    "plain_language_bg": "Приет бюджет на Община Пловдив за 2012 г. (193 344 980 лв.) според решение на Общински съвет - Пловдив.",
    "plain_language_en": "Adopted Plovdiv Municipality budget for 2012 (BGN 193,344,980), from a Plovdiv Municipal Council decision.",
    "source_document": {
      "title": "Общински съвет - Пловдив, Решение 66 за бюджет 2012",
      "url": "https://plovdiv.bg/obs/%D0%B4%D0%B5%D0%B9%D1%81%D1%82%D0%B2%D0%B0%D1%89%D0%B8-%D0%B0%D0%BA%D1%82%D0%BE%D0%B2%D0%B5/%D1%80%D0%B5%D1%88%D0%B5%D0%BD%D0%B8%D0%B5-66/",
      "accessed_at": "2026-06-17"
    },
    "data_quality": "manual_reviewed",
    "title_de": "Gesamtbudget 2012",
    "title_fr": "Budget total 2012",
    "title_it": "Bilancio totale 2012",
    "title_tr": "Toplam 2012 bütçesi",
    "title_es": "Presupuesto total para 2012",
    "plain_language_de": "Verabschiedung des Haushalts der Gemeinde Plovdiv für 2012 (193.344.980 BGN), basierend auf einem Beschluss des Gemeinderats von Plovdiv.",
    "plain_language_fr": "Adoption du budget de la municipalité de Plovdiv pour 2012 (193 344 980 BGN), sur décision du conseil municipal de Plovdiv.",
    "plain_language_it": "Adottato il bilancio del Comune di Plovdiv per il 2012 (193.344.980 BGN), in base a una decisione del Consiglio municipale di Plovdiv.",
    "plain_language_tr": "Plovdiv Belediye Meclisi kararından 2012 yılı Plovdiv Belediyesi bütçesi (193.344.980 BGN) kabul edildi.",
    "plain_language_es": "Se adoptó el presupuesto del municipio de Plovdiv para 2012 (193.344.980 BGN), a partir de una decisión del Consejo Municipal de Plovdiv."
  },
  {
    "id": "budget-plovdiv-2013-capital-programme",
    "year": 2013,
    "municipality": "plovdiv",
    "kind": "summary",
    "summary_key": "capital_programme",
    "category": "other",
    "title_bg": "Капиталова програма за 2013 г.",
    "title_en": "2013 capital programme",
    "amount_bgn": 10105064,
    "currency": "BGN",
    "plain_language_bg": "Разчет за финансиране на капиталовите разходи през 2013 г. (10 105 064 лв.).",
    "plain_language_en": "Capital-expenditure financing plan for 2013 (BGN 10,105,064).",
    "source_document": {
      "title": "Общински съвет - Пловдив, Решение 509 за бюджет 2013",
      "url": "https://plovdiv.bg/obs/%D0%B4%D0%B5%D0%B9%D1%81%D1%82%D0%B2%D0%B0%D1%89%D0%B8-%D0%B0%D0%BA%D1%82%D0%BE%D0%B2%D0%B5/%D1%80%D0%B5%D1%88%D0%B5%D0%BD%D0%B8%D0%B5-509/",
      "accessed_at": "2026-06-17"
    },
    "data_quality": "manual_reviewed",
    "title_de": "Kapitalprogramm 2013",
    "title_fr": "Programme d'investissement 2013",
    "title_it": "Programma di capitale 2013",
    "title_tr": "2013 sermaye programı",
    "title_es": "programa de capital 2013",
    "plain_language_de": "Investitionsfinanzierungsplan für 2013 (10.105.064 BGN).",
    "plain_language_fr": "Plan de financement des dépenses en capital pour 2013 (10 105 064 BGN).",
    "plain_language_it": "Piano di finanziamento delle spese in conto capitale per il 2013 (10.105.064 BGN).",
    "plain_language_tr": "2013 yılı sermaye harcamaları finansman planı (10.105.064 BGN).",
    "plain_language_es": "Plan de financiación de gastos de capital para 2013 (10.105.064 BGN)."
  },
  {
    "id": "budget-plovdiv-2013-total",
    "year": 2013,
    "municipality": "plovdiv",
    "kind": "summary",
    "summary_key": "total_budget",
    "category": "other",
    "title_bg": "Общ бюджет за 2013 г.",
    "title_en": "Total 2013 budget",
    "amount_bgn": 191486024,
    "currency": "BGN",
    "plain_language_bg": "Приет бюджет на Община Пловдив за 2013 г. (191 486 024 лв.).",
    "plain_language_en": "Adopted Plovdiv Municipality budget for 2013 (BGN 191,486,024).",
    "source_document": {
      "title": "Общински съвет - Пловдив, Решение 509 за бюджет 2013",
      "url": "https://plovdiv.bg/obs/%D0%B4%D0%B5%D0%B9%D1%81%D1%82%D0%B2%D0%B0%D1%89%D0%B8-%D0%B0%D0%BA%D1%82%D0%BE%D0%B2%D0%B5/%D1%80%D0%B5%D1%88%D0%B5%D0%BD%D0%B8%D0%B5-509/",
      "accessed_at": "2026-06-17"
    },
    "data_quality": "manual_reviewed",
    "title_de": "Gesamtbudget 2013",
    "title_fr": "Budget total 2013",
    "title_it": "Bilancio totale 2013",
    "title_tr": "Toplam 2013 bütçesi",
    "title_es": "Presupuesto total 2013",
    "plain_language_de": "Verabschiedung des Haushaltsplans der Gemeinde Plovdiv für 2013 (191.486.024 BGN).",
    "plain_language_fr": "Adoption du budget de la municipalité de Plovdiv pour 2013 (191 486 024 BGN).",
    "plain_language_it": "Adottato il bilancio del comune di Plovdiv per il 2013 (191.486.024 BGN).",
    "plain_language_tr": "2013 yılı Plovdiv Belediyesi bütçesi kabul edildi (191.486.024 BGN).",
    "plain_language_es": "Se aprobó el presupuesto del municipio de Plovdiv para 2013 (191.486.024 BGN)."
  },
  {
    "id": "budget-plovdiv-2014-capital-programme",
    "year": 2014,
    "municipality": "plovdiv",
    "kind": "summary",
    "summary_key": "capital_programme",
    "category": "other",
    "title_bg": "Капиталова програма за 2014 г.",
    "title_en": "2014 capital programme",
    "amount_bgn": 39000000,
    "currency": "BGN",
    "plain_language_bg": "Приблизителна капиталова програма за 2014 г. - близо 39 млн. лв., според публичното представяне на бюджета.",
    "plain_language_en": "Approximate 2014 capital programme - nearly BGN 39M, from the public budget presentation.",
    "source_document": {
      "title": "Община Пловдив - представяне на проектобюджет 2014",
      "url": "https://www.plovdiv.bg/%D0%BA%D0%BC%D0%B5%D1%82%D1%8A%D1%82-%D0%B8%D0%B2%D0%B0%D0%BD-%D1%82%D0%BE%D1%82%D0%B5%D0%B2-%D0%BF%D1%80%D0%B5%D0%B4%D1%81%D1%82%D0%B0%D0%B2%D0%B8-%D0%BF%D1%80%D0%BE%D0%B5%D0%BA%D1%82%D0%B0-%D0%B7/",
      "accessed_at": "2026-06-17"
    },
    "data_quality": "public_source",
    "title_de": "Kapitalprogramm 2014",
    "title_fr": "Programme d'investissement 2014",
    "title_it": "Programma di capitale 2014",
    "title_tr": "2014 sermaye programı",
    "title_es": "programa de capital 2014",
    "plain_language_de": "Ungefähres Kapitalprogramm 2014 – fast 39 Mio. BGN, aus der Vorlage des öffentlichen Haushalts.",
    "plain_language_fr": "Programme d'investissement approximatif pour 2014 - près de 39 millions de BGN, d'après la présentation du budget public.",
    "plain_language_it": "Programma di capitale approssimativo per il 2014 - quasi 39 milioni di BGN, dalla presentazione del bilancio pubblico.",
    "plain_language_tr": "Yaklaşık 2014 sermaye programı - kamu bütçesi sunumundan yaklaşık 39 milyon BGN.",
    "plain_language_es": "Programa de capital aproximado para 2014: casi 39 millones de BGN, según la presentación del presupuesto público."
  },
  {
    "id": "budget-plovdiv-2014-total",
    "year": 2014,
    "municipality": "plovdiv",
    "kind": "summary",
    "summary_key": "total_budget",
    "category": "other",
    "title_bg": "Общ бюджет за 2014 г.",
    "title_en": "Total 2014 budget",
    "amount_bgn": 219257495,
    "currency": "BGN",
    "plain_language_bg": "Приет бюджет на Община Пловдив за 2014 г. (219 257 495 лв.).",
    "plain_language_en": "Adopted Plovdiv Municipality budget for 2014 (BGN 219,257,495).",
    "source_document": {
      "title": "Общински съвет - Пловдив, Решение №4 за бюджет 2014",
      "url": "https://plovdiv.bg/obs/%D0%B4%D0%B5%D0%B9%D1%81%D1%82%D0%B2%D0%B0%D1%89%D0%B8-%D0%B0%D0%BA%D1%82%D0%BE%D0%B2%D0%B5/%D1%80%D0%B5%D1%88%D0%B5%D0%BD%D0%B8%D0%B5-4-3/",
      "accessed_at": "2026-06-17",
      "title_de": "Общински съвет – Пловдив, Beschluss Nr. 4 für 2014",
      "title_fr": "Общински съвет - Пловдив, Решение №4 за бюджет 2014",
      "title_it": "Общински съвет - Пловдив, Решение №4 за бюджет 2014",
      "title_tr": "Общински съвет - Пловдив, Решение №4 за бюджет 2014",
      "title_es": "Общински съвет - Пловдив, Решение №4 за бюджет 2014"
    },
    "data_quality": "manual_reviewed",
    "title_de": "Gesamtbudget 2014",
    "title_fr": "Budget total 2014",
    "title_it": "Bilancio totale 2014",
    "title_tr": "Toplam 2014 bütçesi",
    "title_es": "Presupuesto total 2014",
    "plain_language_de": "Verabschiedung des Haushaltsplans der Gemeinde Plovdiv für 2014 (219.257.495 BGN).",
    "plain_language_fr": "Adoption du budget de la municipalité de Plovdiv pour 2014 (219 257 495 BGN).",
    "plain_language_it": "Adottato il bilancio del Comune di Plovdiv per il 2014 (219.257.495 BGN).",
    "plain_language_tr": "Plovdiv Belediyesi'nin 2014 bütçesi (219.257.495 BGN) kabul edildi.",
    "plain_language_es": "Se adoptó el presupuesto del municipio de Plovdiv para 2014 (219.257.495 BGN)."
  },
  {
    "id": "budget-plovdiv-2015-capital-programme",
    "year": 2015,
    "municipality": "plovdiv",
    "kind": "summary",
    "summary_key": "capital_programme",
    "category": "other",
    "title_bg": "Капиталова програма за 2015 г.",
    "title_en": "2015 capital programme",
    "amount_bgn": 63468864,
    "currency": "BGN",
    "plain_language_bg": "Разчет за финансиране на капиталовите разходи през 2015 г. (63 468 864 лв.).",
    "plain_language_en": "Capital-expenditure financing plan for 2015 (BGN 63,468,864).",
    "source_document": {
      "title": "Община Пловдив - бюджет 2015, Решение №34",
      "url": "https://www.plovdiv.bg/wp-content/uploads/2015/02/%D1%80%D0%B5%D1%88.34-15.pdf",
      "accessed_at": "2026-06-17"
    },
    "data_quality": "manual_reviewed",
    "title_de": "Kapitalprogramm 2015",
    "title_fr": "Programme d'investissement 2015",
    "title_it": "Programma di capitale 2015",
    "title_tr": "2015 sermaye programı",
    "title_es": "programa de capital 2015",
    "plain_language_de": "Investitionsfinanzierungsplan für 2015 (63.468.864 BGN).",
    "plain_language_fr": "Plan de financement des dépenses en capital pour 2015 (63 468 864 BGN).",
    "plain_language_it": "Piano di finanziamento in conto capitale per il 2015 (63.468.864 BGN).",
    "plain_language_tr": "2015 yılı sermaye harcamaları finansman planı (63.468.864 BGN).",
    "plain_language_es": "Plan de financiación de gastos de capital para 2015 (63.468.864 BGN)."
  },
  {
    "id": "budget-plovdiv-2015-total",
    "year": 2015,
    "municipality": "plovdiv",
    "kind": "summary",
    "summary_key": "total_budget",
    "category": "other",
    "title_bg": "Общ бюджет за 2015 г.",
    "title_en": "Total 2015 budget",
    "amount_bgn": 264665694,
    "currency": "BGN",
    "plain_language_bg": "Приет бюджет на Община Пловдив за 2015 г. (264 665 694 лв.) според сканираното решение на Общинския съвет.",
    "plain_language_en": "Adopted Plovdiv Municipality budget for 2015 (BGN 264,665,694), from the scanned council decision.",
    "source_document": {
      "title": "Община Пловдив - бюджет 2015, Решение №34",
      "url": "https://www.plovdiv.bg/wp-content/uploads/2015/02/%D1%80%D0%B5%D1%88.34-15.pdf",
      "accessed_at": "2026-06-17"
    },
    "data_quality": "manual_reviewed",
    "title_de": "Gesamtbudget 2015",
    "title_fr": "Budget total 2015",
    "title_it": "Bilancio totale 2015",
    "title_tr": "Toplam 2015 bütçesi",
    "title_es": "Presupuesto total 2015",
    "plain_language_de": "Verabschiedung des Haushaltsplans der Gemeinde Plovdiv für 2015 (264.665.694 BGN), basierend auf dem eingescannten Ratsbeschluss.",
    "plain_language_fr": "Adoption du budget de la municipalité de Plovdiv pour 2015 (264 665 694 BGN), à partir de la décision numérisée du conseil.",
    "plain_language_it": "Adottato il bilancio del comune di Plovdiv per il 2015 (264.665.694 BGN), dalla decisione del consiglio scannerizzata.",
    "plain_language_tr": "Taranan konsey kararından 2015 yılı Plovdiv Belediyesi bütçesi (264.665.694 BGN) kabul edildi.",
    "plain_language_es": "Se adoptó el presupuesto del municipio de Plovdiv para 2015 (264.665.694 BGN), a partir de la decisión del consejo escaneada."
  },
  {
    "id": "budget-plovdiv-2016-capital-programme",
    "year": 2016,
    "municipality": "plovdiv",
    "kind": "summary",
    "summary_key": "capital_programme",
    "category": "other",
    "title_bg": "Капиталова програма за 2016 г.",
    "title_en": "2016 capital programme",
    "amount_bgn": 47188431,
    "currency": "BGN",
    "plain_language_bg": "Разчет за финансиране на капиталовите разходи през 2016 г. (47 188 431 лв.).",
    "plain_language_en": "Capital-expenditure financing plan for 2016 (BGN 47,188,431).",
    "source_document": {
      "title": "Община Пловдив - бюджет 2016, Решение №5",
      "url": "https://www.plovdiv.bg/wp-content/uploads/2015/11/5-budjet-16.pdf",
      "accessed_at": "2026-06-17"
    },
    "data_quality": "manual_reviewed",
    "title_de": "Kapitalprogramm 2016",
    "title_fr": "Programme d'investissement 2016",
    "title_it": "Programma di capitale 2016",
    "title_tr": "2016 sermaye programı",
    "title_es": "programa de capital 2016",
    "plain_language_de": "Investitionsfinanzierungsplan für 2016 (47.188.431 BGN).",
    "plain_language_fr": "Plan de financement des dépenses en capital pour 2016 (47 188 431 BGN).",
    "plain_language_it": "Piano di finanziamento in conto capitale per il 2016 (47.188.431 BGN).",
    "plain_language_tr": "2016 yılı sermaye harcamaları finansman planı (47.188.431 BGN).",
    "plain_language_es": "Plan de financiación de gastos de capital para 2016 (47.188.431 BGN)."
  },
  {
    "id": "budget-plovdiv-2016-total",
    "year": 2016,
    "municipality": "plovdiv",
    "kind": "summary",
    "summary_key": "total_budget",
    "category": "other",
    "title_bg": "Общ бюджет за 2016 г.",
    "title_en": "Total 2016 budget",
    "amount_bgn": 256167127,
    "currency": "BGN",
    "plain_language_bg": "Приет бюджет на Община Пловдив за 2016 г. (256 167 127 лв.) според сканираното решение на Общинския съвет.",
    "plain_language_en": "Adopted Plovdiv Municipality budget for 2016 (BGN 256,167,127), from the scanned council decision.",
    "source_document": {
      "title": "Община Пловдив - бюджет 2016, Решение №5",
      "url": "https://www.plovdiv.bg/wp-content/uploads/2015/11/5-budjet-16.pdf",
      "accessed_at": "2026-06-17"
    },
    "data_quality": "manual_reviewed",
    "title_de": "Gesamtbudget 2016",
    "title_fr": "Budget total 2016",
    "title_it": "Bilancio totale 2016",
    "title_tr": "Toplam 2016 bütçesi",
    "title_es": "Presupuesto total 2016",
    "plain_language_de": "Verabschiedung des Haushaltsplans der Gemeinde Plovdiv für 2016 (256.167.127 BGN), basierend auf dem eingescannten Ratsbeschluss.",
    "plain_language_fr": "Adoption du budget de la municipalité de Plovdiv pour 2016 (256 167 127 BGN), à partir de la décision numérisée du conseil.",
    "plain_language_it": "Adottato il bilancio del comune di Plovdiv per il 2016 (256.167.127 BGN), dalla decisione del consiglio scannerizzata.",
    "plain_language_tr": "Taranan konsey kararından 2016 yılı Plovdiv Belediyesi bütçesi (256.167.127 BGN) kabul edildi.",
    "plain_language_es": "Se adoptó el presupuesto del municipio de Plovdiv para 2016 (256.167.127 BGN), a partir de la decisión del consejo escaneada."
  },
  {
    "id": "budget-plovdiv-2017-capital-programme",
    "year": 2017,
    "municipality": "plovdiv",
    "kind": "summary",
    "summary_key": "capital_programme",
    "category": "other",
    "title_bg": "Капиталова програма за 2017 г.",
    "title_en": "2017 capital programme",
    "amount_bgn": 47629902,
    "currency": "BGN",
    "plain_language_bg": "Разчет за финансиране на капиталовите разходи през 2017 г. (47 629 902 лв.).",
    "plain_language_en": "Capital-expenditure financing plan for 2017 (BGN 47,629,902).",
    "source_document": {
      "title": "Община Пловдив - бюджет 2017, Решение №18",
      "url": "https://www.plovdiv.bg/wp-content/uploads/2017/02/Reshenie18.Protokol2.26.01.2017.pdf",
      "accessed_at": "2026-06-17"
    },
    "data_quality": "manual_reviewed",
    "title_de": "Kapitalprogramm 2017",
    "title_fr": "Programme d'investissement 2017",
    "title_it": "Programma di capitale 2017",
    "title_tr": "2017 sermaye programı",
    "title_es": "programa de capital 2017",
    "plain_language_de": "Investitionsfinanzierungsplan für 2017 (47.629.902 BGN).",
    "plain_language_fr": "Plan de financement des dépenses en capital pour 2017 (47 629 902 BGN).",
    "plain_language_it": "Piano di finanziamento in conto capitale per il 2017 (47.629.902 BGN).",
    "plain_language_tr": "2017 yılı sermaye harcamaları finansman planı (47.629.902 BGN).",
    "plain_language_es": "Plan de financiación de gastos de capital para 2017 (47.629.902 BGN)."
  },
  {
    "id": "budget-plovdiv-2017-total",
    "year": 2017,
    "municipality": "plovdiv",
    "kind": "summary",
    "summary_key": "total_budget",
    "category": "other",
    "title_bg": "Общ бюджет за 2017 г.",
    "title_en": "Total 2017 budget",
    "amount_bgn": 277750459,
    "currency": "BGN",
    "plain_language_bg": "Приет бюджет на Община Пловдив за 2017 г. (277 750 459 лв.) според сканираното решение на Общинския съвет.",
    "plain_language_en": "Adopted Plovdiv Municipality budget for 2017 (BGN 277,750,459), from the scanned council decision.",
    "source_document": {
      "title": "Община Пловдив - бюджет 2017, Решение №18",
      "url": "https://www.plovdiv.bg/wp-content/uploads/2017/02/Reshenie18.Protokol2.26.01.2017.pdf",
      "accessed_at": "2026-06-17"
    },
    "data_quality": "manual_reviewed",
    "title_de": "Gesamtbudget 2017",
    "title_fr": "Budget total 2017",
    "title_it": "Bilancio totale 2017",
    "title_tr": "Toplam 2017 bütçesi",
    "title_es": "Presupuesto total 2017",
    "plain_language_de": "Verabschiedung des Haushaltsplans der Gemeinde Plovdiv für 2017 (277.750.459 BGN), basierend auf dem eingescannten Ratsbeschluss.",
    "plain_language_fr": "Adoption du budget de la municipalité de Plovdiv pour 2017 (277 750 459 BGN), à partir de la décision numérisée du conseil.",
    "plain_language_it": "Adottato il bilancio del comune di Plovdiv per il 2017 (277.750.459 BGN), dalla decisione del consiglio scannerizzata.",
    "plain_language_tr": "Taranan konsey kararından 2017 yılı Plovdiv Belediyesi bütçesi (277.750.459 BGN) kabul edildi.",
    "plain_language_es": "Se adoptó el presupuesto del municipio de Plovdiv para 2017 (277.750.459 BGN), a partir de la decisión del consejo escaneada."
  },
  {
    "id": "budget-plovdiv-2018-capital-programme",
    "year": 2018,
    "municipality": "plovdiv",
    "kind": "summary",
    "summary_key": "capital_programme",
    "category": "other",
    "title_bg": "Капиталова програма за 2018 г.",
    "title_en": "2018 capital programme",
    "amount_bgn": 88182229,
    "currency": "BGN",
    "plain_language_bg": "Разчет за финансиране на капиталовите разходи през 2018 г. (88 182 229 лв.).",
    "plain_language_en": "Capital-expenditure financing plan for 2018 (BGN 88,182,229).",
    "source_document": {
      "title": "Общински съвет - Пловдив, Решение 33 за бюджет 2018",
      "url": "https://plovdiv.bg/obs/%D0%B4%D0%B5%D0%B9%D1%81%D1%82%D0%B2%D0%B0%D1%89%D0%B8-%D0%B0%D0%BA%D1%82%D0%BE%D0%B2%D0%B5/%D1%80%D0%B5%D1%88%D0%B5%D0%BD%D0%B8%D0%B5-33-7/",
      "accessed_at": "2026-06-17",
      "title_de": "Oberstes Gericht, Beschluss vom 33. September 2018",
      "title_fr": "Общински съвет - Пловдив, 33 décembre 2018",
      "title_it": "Общински съвет - Пловдив, Rassegna 33 di agosto 2018",
      "title_tr": "Общински съвет - Пловдив, Решение 33, Şubat 2018",
      "title_es": "Общински съвет - Пловдив, Решение 33 за бюджет 2018"
    },
    "data_quality": "manual_reviewed",
    "title_de": "Kapitalprogramm 2018",
    "title_fr": "Programme d'investissement 2018",
    "title_it": "Programma di capitale 2018",
    "title_tr": "2018 sermaye programı",
    "title_es": "programa de capital 2018",
    "plain_language_de": "Investitionsfinanzierungsplan für 2018 (88.182.229 BGN).",
    "plain_language_fr": "Plan de financement des dépenses en capital pour 2018 (88 182 229 BGN).",
    "plain_language_it": "Piano di finanziamento in conto capitale per il 2018 (88.182.229 BGN).",
    "plain_language_tr": "2018 yılı sermaye harcamaları finansman planı (88.182.229 BGN).",
    "plain_language_es": "Plan de financiación de gastos de capital para 2018 (88.182.229 BGN)."
  },
  {
    "id": "budget-plovdiv-2018-total",
    "year": 2018,
    "municipality": "plovdiv",
    "kind": "summary",
    "summary_key": "total_budget",
    "category": "other",
    "title_bg": "Общ бюджет за 2018 г.",
    "title_en": "Total 2018 budget",
    "amount_bgn": 323794323,
    "currency": "BGN",
    "plain_language_bg": "Приет бюджет на Община Пловдив за 2018 г. (323 794 323 лв.) според решение на Общински съвет - Пловдив.",
    "plain_language_en": "Adopted Plovdiv Municipality budget for 2018 (BGN 323,794,323), from a Plovdiv Municipal Council decision.",
    "source_document": {
      "title": "Общински съвет - Пловдив, Решение 33 за бюджет 2018",
      "url": "https://plovdiv.bg/obs/%D0%B4%D0%B5%D0%B9%D1%81%D1%82%D0%B2%D0%B0%D1%89%D0%B8-%D0%B0%D0%BA%D1%82%D0%BE%D0%B2%D0%B5/%D1%80%D0%B5%D1%88%D0%B5%D0%BD%D0%B8%D0%B5-33-7/",
      "accessed_at": "2026-06-17",
      "title_de": "Oberstes Gericht, Beschluss vom 33. September 2018",
      "title_fr": "Общински съвет - Пловдив, 33 décembre 2018",
      "title_it": "Общински съвет - Пловдив, Rassegna 33 di agosto 2018",
      "title_tr": "Общински съвет - Пловдив, Решение 33, Şubat 2018",
      "title_es": "Общински съвет - Пловдив, Решение 33 за бюджет 2018"
    },
    "data_quality": "manual_reviewed",
    "title_de": "Gesamtbudget 2018",
    "title_fr": "Budget total 2018",
    "title_it": "Bilancio totale 2018",
    "title_tr": "Toplam 2018 bütçesi",
    "title_es": "Presupuesto total 2018",
    "plain_language_de": "Verabschiedung des Haushalts der Gemeinde Plovdiv für 2018 (323.794.323 BGN), basierend auf einem Beschluss des Gemeinderats von Plovdiv.",
    "plain_language_fr": "Adoption du budget de la municipalité de Plovdiv pour 2018 (323 794 323 BGN), sur décision du conseil municipal de Plovdiv.",
    "plain_language_it": "Adottato il bilancio del Comune di Plovdiv per il 2018 (323.794.323 BGN), in base a una decisione del Consiglio municipale di Plovdiv.",
    "plain_language_tr": "Plovdiv Belediye Meclisi kararından 2018 yılı Plovdiv Belediyesi bütçesi (323.794.323 BGN) kabul edildi.",
    "plain_language_es": "Se adoptó el presupuesto del municipio de Plovdiv para 2018 (323.794.323 BGN), a partir de una decisión del Consejo Municipal de Plovdiv."
  },
  {
    "id": "budget-plovdiv-2019-capital-programme",
    "year": 2019,
    "municipality": "plovdiv",
    "kind": "summary",
    "summary_key": "capital_programme",
    "category": "other",
    "title_bg": "Капиталова програма за 2019 г.",
    "title_en": "2019 capital programme",
    "amount_bgn": 60000000,
    "currency": "BGN",
    "plain_language_bg": "Капиталова програма за 2019 г. - около 60 млн. лв. според съобщение за приемането на бюджета.",
    "plain_language_en": "2019 capital programme - about BGN 60M, from a budget-adoption report.",
    "source_document": {
      "title": "БНР - приет бюджет на Пловдив за 2019 г.",
      "url": "https://old-news.bnr.bg/plovdiv/post/101075189/prieha-budjeta-na-plovdiv-kapitalovata-programa-e-za-60-miliona-leva",
      "accessed_at": "2026-06-14"
    },
    "data_quality": "public_source",
    "title_de": "Kapitalprogramm 2019",
    "title_fr": "Programme d'investissement 2019",
    "title_it": "Programma di capitale 2019",
    "title_tr": "2019 sermaye programı",
    "title_es": "programa de capital 2019",
    "plain_language_de": "Kapitalprogramm 2019 – etwa 60 Mio. BGN, aus einem Haushaltsverabschiedungsbericht.",
    "plain_language_fr": "Programme d'investissement 2019 - environ 60 millions de BGN, d'après un rapport d'adoption du budget.",
    "plain_language_it": "Programma di capitale 2019 - circa 60 milioni di BGN, da un rapporto sull'adozione del budget.",
    "plain_language_tr": "2019 sermaye programı - bütçe kabul raporundan yaklaşık 60 milyon BGN.",
    "plain_language_es": "Programa de capital para 2019: alrededor de 60 millones de BGN, según un informe de adopción del presupuesto."
  },
  {
    "id": "budget-plovdiv-2019-total",
    "year": 2019,
    "municipality": "plovdiv",
    "kind": "summary",
    "summary_key": "total_budget",
    "category": "other",
    "title_bg": "Общ бюджет за 2019 г.",
    "title_en": "Total 2019 budget",
    "amount_bgn": 341959020,
    "currency": "BGN",
    "plain_language_bg": "Приет бюджет на Община Пловдив за 2019 г. (341 959 020 лв.).",
    "plain_language_en": "Adopted Plovdiv Municipality budget for 2019 (BGN 341,959,020).",
    "source_document": {
      "title": "БНР — приет бюджет на Пловдив за 2019 г.",
      "url": "https://old-news.bnr.bg/plovdiv/post/101075189/prieha-budjeta-na-plovdiv-kapitalovata-programa-e-za-60-miliona-leva",
      "accessed_at": "2026-06-14"
    },
    "data_quality": "public_source",
    "title_de": "Gesamtbudget 2019",
    "title_fr": "Budget total 2019",
    "title_it": "Bilancio totale 2019",
    "title_tr": "Toplam 2019 bütçesi",
    "title_es": "Presupuesto total 2019",
    "plain_language_de": "Verabschiedung des Haushaltsplans der Gemeinde Plovdiv für 2019 (341.959.020 BGN).",
    "plain_language_fr": "Adoption du budget de la municipalité de Plovdiv pour 2019 (341 959 020 BGN).",
    "plain_language_it": "Adottato il bilancio del Comune di Plovdiv per il 2019 (341.959.020 BGN).",
    "plain_language_tr": "Plovdiv Belediyesi'nin 2019 bütçesi (341.959.020 BGN) kabul edildi.",
    "plain_language_es": "Presupuesto adoptado por el municipio de Plovdiv para 2019 (341.959.020 BGN)."
  },
  {
    "id": "budget-plovdiv-2020-total",
    "year": 2020,
    "municipality": "plovdiv",
    "kind": "summary",
    "summary_key": "total_budget",
    "category": "other",
    "title_bg": "Общ бюджет за 2020 г.",
    "title_en": "Total 2020 budget",
    "amount_bgn": 343000000,
    "currency": "BGN",
    "plain_language_bg": "Приет бюджет на Община Пловдив за 2020 г. (около 343 млн. лв.: 186 млн. държавни и 157 млн. собствени приходи).",
    "plain_language_en": "Adopted Plovdiv Municipality budget for 2020 (about BGN 343M: BGN 186M state and BGN 157M local revenue).",
    "source_document": {
      "title": "Община Пловдив — бюджет за 2020 г.",
      "url": "https://www.plovdiv.bg/slider/%D0%B1%D1%8E%D0%B4%D0%B6%D0%B5%D1%82-%D0%B7%D0%B0-2020-%D0%B3%D0%BE%D0%B4%D0%B8%D0%BD%D0%B0/",
      "accessed_at": "2026-06-14"
    },
    "data_quality": "public_source",
    "title_de": "Gesamtbudget 2020",
    "title_fr": "Budget total 2020",
    "title_it": "Bilancio totale 2020",
    "title_tr": "Toplam 2020 bütçesi",
    "title_es": "Presupuesto total 2020",
    "plain_language_de": "Verabschiedung des Budgets der Gemeinde Plovdiv für 2020 (ca. 343 Mio. BGN: 186 Mio. BGN staatliche und 157 Mio. BGN lokale Einnahmen).",
    "plain_language_fr": "Adoption du budget de la municipalité de Plovdiv pour 2020 (environ 343 millions de BGN : 186 millions de BGN pour l'État et 157 millions de BGN pour les recettes locales).",
    "plain_language_it": "Adottato il bilancio del comune di Plovdiv per il 2020 (circa 343 milioni di BGN: 186 milioni di BGN statali e 157 milioni di BGN entrate locali).",
    "plain_language_tr": "Plovdiv Belediyesi'nin 2020 bütçesi kabul edildi (yaklaşık 343 milyon BGN: 186 milyon BGN devlet geliri ve 157 milyon BGN yerel gelir).",
    "plain_language_es": "Se adoptó el presupuesto del municipio de Plovdiv para 2020 (alrededor de 343 millones de BGN: 186 millones de BGN estatales y 157 millones de BGN locales)."
  },
  {
    "id": "budget-plovdiv-2021-total",
    "year": 2021,
    "municipality": "plovdiv",
    "kind": "summary",
    "summary_key": "total_budget",
    "category": "other",
    "title_bg": "Общ бюджет за 2021 г.",
    "title_en": "Total 2021 budget",
    "amount_bgn": 345631629,
    "currency": "BGN",
    "plain_language_bg": "Първоначално гласуван бюджет на Община Пловдив за 2021 г. (345 631 629 лв.; по-късно актуализиран до около 400 млн. лв.).",
    "plain_language_en": "Initially adopted Plovdiv Municipality budget for 2021 (BGN 345,631,629; later updated to about BGN 400M).",
    "source_document": {
      "title": "Марица — бюджет на Пловдив за 2021 г.",
      "url": "https://www.marica.bg/plovdiv/politika/byudjetat-na-plovdiv-za-2021-g-mestnite-danaci-i-taksi-bez-promqna-izbivat-lipsite-s-po-skapi-uslugi",
      "accessed_at": "2026-06-14"
    },
    "data_quality": "public_source",
    "title_de": "Gesamtbudget 2021",
    "title_fr": "Budget total 2021",
    "title_it": "Bilancio totale 2021",
    "title_tr": "Toplam 2021 bütçesi",
    "title_es": "Presupuesto total 2021",
    "plain_language_de": "Ursprünglich verabschiedeter Haushalt der Gemeinde Plovdiv für 2021 (345.631.629 BGN; später auf etwa 400 Mio. BGN aktualisiert).",
    "plain_language_fr": "Budget de la municipalité de Plovdiv initialement adopté pour 2021 (345 631 629 BGN ; mis à jour plus tard à environ 400 millions de BGN).",
    "plain_language_it": "Bilancio inizialmente adottato dal comune di Plovdiv per il 2021 (345.631.629 BGN; successivamente aggiornato a circa 400 milioni di BGN).",
    "plain_language_tr": "Başlangıçta Plovdiv Belediyesi'nin 2021 bütçesi kabul edildi (345.631.629 BGN; daha sonra yaklaşık 400 milyon BGN olarak güncellendi).",
    "plain_language_es": "Presupuesto inicialmente adoptado por el municipio de Plovdiv para 2021 (345.631.629 BGN; posteriormente actualizado a aproximadamente 400 millones de BGN)."
  },
  {
    "id": "budget-plovdiv-2022-total",
    "year": 2022,
    "municipality": "plovdiv",
    "kind": "summary",
    "summary_key": "total_budget",
    "category": "other",
    "title_bg": "Общ бюджет за 2022 г.",
    "title_en": "Total 2022 budget",
    "amount_bgn": 526000000,
    "currency": "BGN",
    "plain_language_bg": "Приет бюджет на Община Пловдив за 2022 г. (приблизително, по съобщения за приемането).",
    "plain_language_en": "Adopted Plovdiv Municipality budget for 2022 (approximate, per adoption reports).",
    "source_document": {
      "title": "news.bg — приет бюджет на Пловдив за 2022 г.",
      "url": "https://news.bg/politics/prieha-rekorden-byudzhet-na-obshtina-plovdiv-nad-526-mln-lv.html",
      "accessed_at": "2026-06-14"
    },
    "data_quality": "public_source",
    "title_de": "Gesamtbudget 2022",
    "title_fr": "Budget total 2022",
    "title_it": "Bilancio totale 2022",
    "title_tr": "Toplam 2022 bütçesi",
    "title_es": "Presupuesto total 2022",
    "plain_language_de": "Verabschiedetes Budget der Gemeinde Plovdiv für 2022 (ungefähr, je Annahmebericht).",
    "plain_language_fr": "Adoption du budget de la municipalité de Plovdiv pour 2022 (rapports approximatifs par adoption).",
    "plain_language_it": "Budget adottato dal comune di Plovdiv per il 2022 (approssimativo, secondo i rapporti di adozione).",
    "plain_language_tr": "Plovdiv Belediyesi'nin 2022 bütçesi kabul edildi (kabul raporları başına yaklaşık değer).",
    "plain_language_es": "Presupuesto adoptado por el municipio de Plovdiv para 2022 (aproximado, según informes de adopción)."
  },
  {
    "id": "budget-plovdiv-2023-total",
    "year": 2023,
    "municipality": "plovdiv",
    "kind": "summary",
    "summary_key": "total_budget",
    "category": "other",
    "title_bg": "Общ бюджет за 2023 г.",
    "title_en": "Total 2023 budget",
    "amount_bgn": 655255005,
    "currency": "BGN",
    "plain_language_bg": "Бюджет на Община Пловдив за 2023 г. (655 255 005 лв.).",
    "plain_language_en": "Plovdiv Municipality budget for 2023 (BGN 655,255,005).",
    "source_document": {
      "title": "Focus News — бюджет на Пловдив за 2023 г.",
      "url": "https://www.focus-news.net/novini/regioni/Proektobyudzhetut-na-Plovdiv-za-2023-g-e-655-255-005-leva-13-otiva-za-zaplati-1795125",
      "accessed_at": "2026-06-14"
    },
    "data_quality": "public_source",
    "title_de": "Gesamtbudget 2023",
    "title_fr": "Budget total 2023",
    "title_it": "Bilancio totale 2023",
    "title_tr": "Toplam 2023 bütçesi",
    "title_es": "Presupuesto total 2023",
    "plain_language_de": "Haushalt der Gemeinde Plovdiv für 2023 (655.255.005 BGN).",
    "plain_language_fr": "Budget de la municipalité de Plovdiv pour 2023 (655 255 005 BGN).",
    "plain_language_it": "Bilancio del comune di Plovdiv per il 2023 (655.255.005 BGN).",
    "plain_language_tr": "Plovdiv Belediyesi'nin 2023 bütçesi (655.255.005 BGN).",
    "plain_language_es": "Presupuesto del municipio de Plovdiv para 2023 (655.255.005 BGN)."
  },
  {
    "id": "budget-plovdiv-2024-capital-programme",
    "year": 2024,
    "municipality": "plovdiv",
    "kind": "summary",
    "summary_key": "capital_programme",
    "category": "other",
    "title_bg": "Капиталова програма за 2024 г.",
    "title_en": "2024 capital programme",
    "amount_bgn": 123375273,
    "currency": "BGN",
    "plain_language_bg": "Общ размер на капиталовата програма за 2024 г. (123 375 273 лв., включва държавни и европейски средства).",
    "plain_language_en": "Total size of the 2024 capital programme (BGN 123,375,273; includes state and European funds).",
    "source_document": {
      "title": "Марица — бюджет 2024 на Пловдив (капиталова програма)",
      "url": "https://www.marica.bg/plovdiv/gradat/byudjet-2024-na-plovdiv-nay-mnogo-pari-za-obrazovanie-nqma-da-se-vdigat-danacite",
      "accessed_at": "2026-06-14"
    },
    "data_quality": "public_source",
    "title_de": "Kapitalprogramm 2024",
    "title_fr": "Programme d'investissement 2024",
    "title_it": "Programma di capitale 2024",
    "title_tr": "2024 sermaye programı",
    "title_es": "programa de capital 2024",
    "plain_language_de": "Gesamtumfang des Kapitalprogramms 2024 (123.375.273 BGN; einschließlich staatlicher und europäischer Mittel).",
    "plain_language_fr": "Montant total du programme d'investissement 2024 (123 375 273 BGN ; comprend les fonds publics et européens).",
    "plain_language_it": "Dimensione totale del programma di capitale 2024 (123.375.273 BGN; include fondi statali ed europei).",
    "plain_language_tr": "2024 sermaye programının toplam büyüklüğü (123.375.273 BGN; devlet ve Avrupa fonlarını içerir).",
    "plain_language_es": "Tamaño total del programa de capital para 2024 (123.375.273 BGN; incluye fondos estatales y europeos)."
  },
  {
    "id": "budget-plovdiv-2024-total",
    "year": 2024,
    "municipality": "plovdiv",
    "kind": "summary",
    "summary_key": "total_budget",
    "category": "other",
    "title_bg": "Общ бюджет за 2024 г.",
    "title_en": "Total 2024 budget",
    "amount_bgn": 684000000,
    "currency": "BGN",
    "plain_language_bg": "Бюджет на Община Пловдив за 2024 г. (приблизително; ръст от около 29 млн. лв. спрямо 2023 г.).",
    "plain_language_en": "Plovdiv Municipality budget for 2024 (approximate; an increase of about BGN 29M over 2023).",
    "source_document": {
      "title": "Марица — бюджет на Пловдив за 2024 г. (ръст 29 млн. лв.)",
      "url": "https://www.marica.bg/plovdiv/gradat/byudjetat-na-plovdiv-pod-indigo-samo-29-mln-leva-rast",
      "accessed_at": "2026-06-14"
    },
    "data_quality": "public_source",
    "title_de": "Gesamtbudget 2024",
    "title_fr": "Budget total 2024",
    "title_it": "Bilancio totale 2024",
    "title_tr": "Toplam 2024 bütçesi",
    "title_es": "Presupuesto total para 2024",
    "plain_language_de": "Budget der Gemeinde Plovdiv für 2024 (ungefähr; eine Steigerung von etwa 29 Mio. BGN gegenüber 2023).",
    "plain_language_fr": "Budget de la municipalité de Plovdiv pour 2024 (approximatif ; une augmentation d'environ 29 millions de BGN par rapport à 2023).",
    "plain_language_it": "Bilancio del comune di Plovdiv per il 2024 (approssimativo; un aumento di circa 29 milioni di BGN rispetto al 2023).",
    "plain_language_tr": "Plovdiv Belediyesi'nin 2024 bütçesi (yaklaşık; 2023'e göre yaklaşık 29 milyon BGN artış).",
    "plain_language_es": "Presupuesto del municipio de Plovdiv para 2024 (aproximado; un aumento de aproximadamente 29 millones de BGN con respecto a 2023)."
  },
  {
    "id": "budget-plovdiv-2025-capital-programme",
    "year": 2025,
    "municipality": "plovdiv",
    "kind": "summary",
    "summary_key": "capital_programme",
    "category": "other",
    "title_bg": "Капиталова програма за 2025 г.",
    "title_en": "2025 capital programme",
    "amount_bgn": 139597929,
    "currency": "BGN",
    "plain_language_bg": "Общият размер на капиталовата програма за 2025 г.",
    "plain_language_en": "The total size of the 2025 capital programme.",
    "source_document": {
      "title": "Община Пловдив — представяне на Бюджет 2025",
      "url": "https://www.plovdiv.bg/presentation-budget-2025/",
      "accessed_at": "2026-06-14"
    },
    "data_quality": "public_source",
    "title_de": "Kapitalprogramm 2025",
    "title_fr": "Programme d'investissement 2025",
    "title_it": "Programma di capitale 2025",
    "title_tr": "2025 sermaye programı",
    "title_es": "programa de capital 2025",
    "plain_language_de": "Der Gesamtumfang des Kapitalprogramms 2025.",
    "plain_language_fr": "La taille totale du programme d’investissement 2025.",
    "plain_language_it": "La dimensione totale del programma di capitale per il 2025.",
    "plain_language_tr": "2025 sermaye programının toplam büyüklüğü.",
    "plain_language_es": "El tamaño total del programa de capital para 2025."
  },
  {
    "id": "budget-plovdiv-2025-culture",
    "year": 2025,
    "municipality": "plovdiv",
    "category": "culture",
    "title_bg": "Култура",
    "title_en": "Culture",
    "amount_bgn": 7957082,
    "share_percent": 5.7,
    "plain_language_bg": "Културна инфраструктура и публични пространства с културна стойност (приблизителна стойност по публикувания дял).",
    "plain_language_en": "Cultural infrastructure and public spaces with cultural value (approximate value from the published share).",
    "source_document": {
      "title": "Община Пловдив — представяне на Бюджет 2025",
      "url": "https://www.plovdiv.bg/presentation-budget-2025/",
      "accessed_at": "2026-06-14"
    },
    "data_quality": "public_source",
    "kind": "sector",
    "currency": "BGN",
    "title_de": "Kultur",
    "title_fr": "Culturel",
    "title_it": "Cultura",
    "title_tr": "Kültür",
    "title_es": "Cultura",
    "plain_language_de": "Kulturelle Infrastruktur und öffentliche Räume mit kulturellem Wert (ungefährer Wert aus dem veröffentlichten Anteil).",
    "plain_language_fr": "Infrastructures culturelles et espaces publics à valeur culturelle (valeur approximative de la part publiée).",
    "plain_language_it": "Infrastrutture culturali e spazi pubblici con valore culturale (valore approssimativo dalla quota pubblicata).",
    "plain_language_tr": "Kültürel değere sahip kültürel altyapı ve kamusal alanlar (yayınlanan paylaşıma göre yaklaşık değer).",
    "plain_language_es": "Infraestructura cultural y espacios públicos con valor cultural (valor aproximado de la participación publicada)."
  },
  {
    "id": "budget-plovdiv-2025-education",
    "year": 2025,
    "municipality": "plovdiv",
    "category": "education",
    "title_bg": "Образование",
    "title_en": "Education",
    "amount_bgn": 61702285,
    "share_percent": 44.2,
    "plain_language_bg": "Най-големият дял от капиталовата програма за 2025 г. — училища, детски градини и образователна среда (приблизителна стойност по публикувания дял).",
    "plain_language_en": "The largest share of the 2025 capital programme — schools, kindergartens and educational facilities (approximate value from the published share).",
    "source_document": {
      "title": "Община Пловдив — представяне на Бюджет 2025",
      "url": "https://www.plovdiv.bg/presentation-budget-2025/",
      "accessed_at": "2026-06-14"
    },
    "data_quality": "public_source",
    "kind": "sector",
    "currency": "BGN",
    "title_de": "Bildung",
    "title_fr": "Éducation",
    "title_it": "Istruzione",
    "title_tr": "Eğitim",
    "title_es": "educación",
    "plain_language_de": "Der größte Anteil des Kapitalprogramms 2025 sind Schulen, Kindergärten und Bildungseinrichtungen (ungefährer Wert aus dem veröffentlichten Anteil).",
    "plain_language_fr": "La plus grande part du programme d'investissement 2025 est constituée d'écoles, de jardins d'enfants et d'établissements d'enseignement (valeur approximative de la part publiée).",
    "plain_language_it": "La quota maggiore del programma di capitale 2025 — scuole, asili nido e strutture educative (valore approssimativo dalla quota pubblicata).",
    "plain_language_tr": "2025 sermaye programında en büyük pay okullar, anaokulları ve eğitim tesisleridir (yayınlanan paya göre yaklaşık değer).",
    "plain_language_es": "La mayor parte del programa de capital para 2025 son escuelas, guarderías e instalaciones educativas (valor aproximado de la proporción publicada)."
  },
  {
    "id": "budget-plovdiv-2025-environment",
    "year": 2025,
    "municipality": "plovdiv",
    "category": "environment",
    "title_bg": "Околна среда, чистота и улици",
    "title_en": "Environment, cleanliness and streets",
    "amount_bgn": 26523607,
    "share_percent": 19,
    "plain_language_bg": "Опазване на околната среда, чистота, благоустрояване и ремонт на улици (приблизителна стойност по публикувания дял).",
    "plain_language_en": "Environmental protection, cleanliness, improvement and street repairs (approximate value from the published share).",
    "source_document": {
      "title": "Община Пловдив — представяне на Бюджет 2025",
      "url": "https://www.plovdiv.bg/presentation-budget-2025/",
      "accessed_at": "2026-06-14"
    },
    "data_quality": "public_source",
    "kind": "sector",
    "currency": "BGN",
    "title_de": "Umwelt, Sauberkeit und Straßen",
    "title_fr": "Environnement, propreté et rues",
    "title_it": "Ambiente, pulizia e strade",
    "title_tr": "Çevre, temizlik ve sokaklar",
    "title_es": "Medio ambiente, limpieza y calles.",
    "plain_language_de": "Umweltschutz, Sauberkeit, Verbesserung und Straßenreparaturen (ungefährer Wert aus dem veröffentlichten Anteil).",
    "plain_language_fr": "Protection de l'environnement, propreté, amélioration et réparation des rues (valeur approximative de la part publiée).",
    "plain_language_it": "Tutela dell'ambiente, pulizia, miglioramento e riparazione delle strade (valore approssimativo dalla quota pubblicata).",
    "plain_language_tr": "Çevre koruma, temizlik, iyileştirme ve sokak onarımları (yayınlanan paydan yaklaşık değer).",
    "plain_language_es": "Protección ambiental, limpieza, mejoramiento y reparación de calles (valor aproximado de la participación publicada)."
  },
  {
    "id": "budget-plovdiv-2025-other",
    "year": 2025,
    "municipality": "plovdiv",
    "category": "other",
    "title_bg": "Други капиталови разходи",
    "title_en": "Other capital expenditure",
    "amount_bgn": 24429637,
    "share_percent": 17.5,
    "plain_language_bg": "Останалата част от капиталовата програма извън посочените сектори (приблизителна стойност).",
    "plain_language_en": "The remaining part of the capital programme outside the listed sectors (approximate value).",
    "source_document": {
      "title": "Община Пловдив — представяне на Бюджет 2025",
      "url": "https://www.plovdiv.bg/presentation-budget-2025/",
      "accessed_at": "2026-06-14"
    },
    "data_quality": "public_source",
    "kind": "sector",
    "currency": "BGN",
    "title_de": "Sonstige Investitionen",
    "title_fr": "Autres dépenses en capital",
    "title_it": "Altre spese in conto capitale",
    "title_tr": "Diğer sermaye harcamaları",
    "title_es": "Otros gastos de capital",
    "plain_language_de": "Der verbleibende Teil des Kapitalprogramms außerhalb der aufgeführten Sektoren (ungefährer Wert).",
    "plain_language_fr": "La partie restante du programme d'investissement en dehors des secteurs répertoriés (valeur approximative).",
    "plain_language_it": "La restante parte del programma di capitale al di fuori dei settori elencati (valore approssimativo).",
    "plain_language_tr": "Sermaye programının listelenen sektörler dışında kalan kısmı (yaklaşık değer).",
    "plain_language_es": "La parte restante del programa de capital fuera de los sectores cotizados (valor aproximado)."
  },
  {
    "id": "budget-plovdiv-2025-social",
    "year": 2025,
    "municipality": "plovdiv",
    "category": "social",
    "title_bg": "Социални дейности",
    "title_en": "Social activities",
    "amount_bgn": 13122205,
    "share_percent": 9.4,
    "plain_language_bg": "Социална подкрепа и свързана инфраструктура (приблизителна стойност по публикувания дял).",
    "plain_language_en": "Social support and related infrastructure (approximate value from the published share).",
    "source_document": {
      "title": "Община Пловдив — представяне на Бюджет 2025",
      "url": "https://www.plovdiv.bg/presentation-budget-2025/",
      "accessed_at": "2026-06-14"
    },
    "data_quality": "public_source",
    "kind": "sector",
    "currency": "BGN",
    "title_de": "Soziale Aktivitäten",
    "title_fr": "Activités sociales",
    "title_it": "Attività sociali",
    "title_tr": "Sosyal aktiviteler",
    "title_es": "actividades sociales",
    "plain_language_de": "Soziale Unterstützung und zugehörige Infrastruktur (ungefährer Wert aus dem veröffentlichten Anteil).",
    "plain_language_fr": "Soutien social et infrastructures associées (valeur approximative de la part publiée).",
    "plain_language_it": "Supporto sociale e relative infrastrutture (valore approssimativo dalla quota pubblicata).",
    "plain_language_tr": "Sosyal destek ve ilgili altyapı (yayınlanan paylaşımdan alınan yaklaşık değer).",
    "plain_language_es": "Apoyo social e infraestructura relacionada (valor aproximado de la participación publicada)."
  },
  {
    "id": "budget-plovdiv-2025-sport",
    "year": 2025,
    "municipality": "plovdiv",
    "category": "sport",
    "title_bg": "Спорт",
    "title_en": "Sport",
    "amount_bgn": 5863113,
    "share_percent": 4.2,
    "plain_language_bg": "Спортна инфраструктура, включително стадиони и зали (приблизителна стойност по публикувания дял).",
    "plain_language_en": "Sports infrastructure, including stadiums and halls (approximate value from the published share).",
    "source_document": {
      "title": "Община Пловдив — представяне на Бюджет 2025",
      "url": "https://www.plovdiv.bg/presentation-budget-2025/",
      "accessed_at": "2026-06-14"
    },
    "data_quality": "public_source",
    "kind": "sector",
    "currency": "BGN",
    "title_de": "Sport",
    "title_fr": "Sport",
    "title_it": "Sport",
    "title_tr": "Spor",
    "title_es": "deporte",
    "plain_language_de": "Sportinfrastruktur, einschließlich Stadien und Hallen (ungefährer Wert aus dem veröffentlichten Anteil).",
    "plain_language_fr": "Infrastructures sportives, y compris stades et salles (valeur approximative de la part publiée).",
    "plain_language_it": "Infrastrutture sportive, inclusi stadi e palazzetti (valore approssimativo dalla quota pubblicata).",
    "plain_language_tr": "Stadyumlar ve salonlar dahil spor altyapısı (yayınlanan paya göre yaklaşık değer).",
    "plain_language_es": "Infraestructura deportiva, incluidos estadios y pabellones (valor aproximado de la participación publicada)."
  },
  {
    "id": "budget-plovdiv-2025-total",
    "year": 2025,
    "municipality": "plovdiv",
    "kind": "summary",
    "summary_key": "total_budget",
    "category": "other",
    "title_bg": "Общ бюджет за 2025 г.",
    "title_en": "Total 2025 budget",
    "amount_bgn": 715154301,
    "currency": "BGN",
    "plain_language_bg": "Общата рамка на бюджета на Община Пловдив за 2025 г.",
    "plain_language_en": "The total 2025 budget framework for Plovdiv Municipality.",
    "source_document": {
      "title": "Община Пловдив — представяне на Бюджет 2025",
      "url": "https://www.plovdiv.bg/presentation-budget-2025/",
      "accessed_at": "2026-06-14"
    },
    "data_quality": "public_source",
    "title_de": "Gesamtbudget 2025",
    "title_fr": "Budget total 2025",
    "title_it": "Bilancio totale 2025",
    "title_tr": "Toplam 2025 bütçesi",
    "title_es": "Presupuesto total para 2025",
    "plain_language_de": "Der Gesamthaushaltsrahmen 2025 für die Gemeinde Plovdiv.",
    "plain_language_fr": "Le cadre budgétaire total 2025 pour la municipalité de Plovdiv.",
    "plain_language_it": "Il quadro di bilancio totale per il 2025 per il comune di Plovdiv.",
    "plain_language_tr": "Plovdiv Belediyesi için toplam 2025 bütçe çerçevesi.",
    "plain_language_es": "El marco presupuestario total para 2025 para el municipio de Plovdiv."
  },
  {
    "id": "budget-plovdiv-2026-eu-funds",
    "year": 2026,
    "municipality": "plovdiv",
    "kind": "funding_source",
    "funding_key": "eu_funds",
    "display_order": 1,
    "category": "other",
    "title_bg": "Европейски средства",
    "title_en": "European funds",
    "amount_eur": 51100000,
    "currency": "EUR",
    "plain_language_bg": "Най-големият източник в прогнозната капиталова програма за 2026 г.",
    "plain_language_en": "The largest funding source in the provisional 2026 capital programme.",
    "source_document": {
      "title": "Под тепето — капиталова програма за 2026 г.",
      "url": "https://podtepeto.com/aktualno/obsthina-plovdiv-planira-blizo-87-mln-evro-za-kapitalovi-razhodi-prez-2026-g/",
      "accessed_at": "2026-06-14"
    },
    "data_quality": "provisional",
    "title_de": "Europäische Fonds",
    "title_fr": "Fonds européens",
    "title_it": "Fondi europei",
    "title_tr": "Avrupa fonları",
    "title_es": "fondos europeos",
    "plain_language_de": "Die größte Finanzierungsquelle im vorläufigen Kapitalprogramm 2026.",
    "plain_language_fr": "La plus grande source de financement du programme d’investissement provisoire 2026.",
    "plain_language_it": "La principale fonte di finanziamento nel programma provvisorio di capitale 2026.",
    "plain_language_tr": "Geçici 2026 sermaye programındaki en büyük finansman kaynağı.",
    "plain_language_es": "La mayor fuente de financiación del programa de capital provisional para 2026."
  },
  {
    "id": "budget-plovdiv-2026-other-sources",
    "year": 2026,
    "municipality": "plovdiv",
    "kind": "funding_source",
    "funding_key": "other_sources",
    "display_order": 5,
    "category": "other",
    "title_bg": "Други източници",
    "title_en": "Other sources",
    "amount_eur": 5080000,
    "currency": "EUR",
    "plain_language_bg": "Други източници, включително дарения, средства от ПУДООС и заеми.",
    "plain_language_en": "Other sources, including donations, PUDOOS funds and loans.",
    "source_document": {
      "title": "Под тепето — капиталова програма за 2026 г.",
      "url": "https://podtepeto.com/aktualno/obsthina-plovdiv-planira-blizo-87-mln-evro-za-kapitalovi-razhodi-prez-2026-g/",
      "accessed_at": "2026-06-14"
    },
    "data_quality": "provisional",
    "title_de": "Andere Quellen",
    "title_fr": "Autres sources",
    "title_it": "Altre fonti",
    "title_tr": "Diğer kaynaklar",
    "title_es": "Otras fuentes",
    "plain_language_de": "Andere Quellen, einschließlich Spenden, PUDOOS-Mittel und Darlehen.",
    "plain_language_fr": "Autres sources, notamment les dons, les fonds PUDOOS et les prêts.",
    "plain_language_it": "Altre fonti, tra cui donazioni, fondi PUDOOS e prestiti.",
    "plain_language_tr": "Bağışlar, PUDOOS fonları ve krediler dahil diğer kaynaklar.",
    "plain_language_es": "Otras fuentes, incluidas donaciones, fondos y préstamos de PUDOOS."
  },
  {
    "id": "budget-plovdiv-2026-own-remainder",
    "year": 2026,
    "municipality": "plovdiv",
    "kind": "funding_source",
    "funding_key": "own_remainder",
    "display_order": 2,
    "category": "other",
    "title_bg": "Собствени приходи и преходен остатък",
    "title_en": "Own revenue and carry-over balance",
    "amount_eur": 20900000,
    "currency": "EUR",
    "plain_language_bg": "Собствени средства на общината и преходен остатък.",
    "plain_language_en": "Municipal own revenue and carry-over balance.",
    "source_document": {
      "title": "Под тепето — капиталова програма за 2026 г.",
      "url": "https://podtepeto.com/aktualno/obsthina-plovdiv-planira-blizo-87-mln-evro-za-kapitalovi-razhodi-prez-2026-g/",
      "accessed_at": "2026-06-14"
    },
    "data_quality": "provisional",
    "title_de": "Eigene Einnahmen und Übertragssaldo",
    "title_fr": "Recettes propres et solde reporté",
    "title_it": "Entrate proprie e saldo riportato",
    "title_tr": "Kendi geliri ve devreden bakiye",
    "title_es": "Ingresos propios y saldo arrastrado",
    "plain_language_de": "Kommunale Eigeneinnahmen und Übertragssaldo.",
    "plain_language_fr": "Recettes propres communales et solde reporté.",
    "plain_language_it": "Entrate proprie comunali e saldo di riporto.",
    "plain_language_tr": "Belediye öz geliri ve devreden bakiye.",
    "plain_language_es": "Ingresos propios municipales y saldo prorrogado."
  },
  {
    "id": "budget-plovdiv-2026-programme-cofinancing",
    "year": 2026,
    "municipality": "plovdiv",
    "kind": "funding_source",
    "funding_key": "programme_cofinancing",
    "display_order": 3,
    "category": "other",
    "title_bg": "Съфинансиране по програми",
    "title_en": "Programme co-financing",
    "amount_eur": 7130000,
    "currency": "EUR",
    "plain_language_bg": "Съфинансиране по оперативни и други програми.",
    "plain_language_en": "Co-financing under operational and other programmes.",
    "source_document": {
      "title": "Под тепето — капиталова програма за 2026 г.",
      "url": "https://podtepeto.com/aktualno/obsthina-plovdiv-planira-blizo-87-mln-evro-za-kapitalovi-razhodi-prez-2026-g/",
      "accessed_at": "2026-06-14"
    },
    "data_quality": "provisional",
    "title_de": "Kofinanzierung des Programms",
    "title_fr": "Cofinancement du programme",
    "title_it": "Cofinanziamento del programma",
    "title_tr": "Program ortak finansmanı",
    "title_es": "Cofinanciamiento del programa",
    "plain_language_de": "Kofinanzierung im Rahmen operativer und anderer Programme.",
    "plain_language_fr": "Cofinancement au titre de programmes opérationnels et autres.",
    "plain_language_it": "Cofinanziamento nell'ambito di programmi operativi e di altro tipo.",
    "plain_language_tr": "Operasyonel ve diğer programlar kapsamında ortak finansman.",
    "plain_language_es": "Cofinanciación en el marco de programas operativos y de otro tipo."
  },
  {
    "id": "budget-plovdiv-2026-state-subsidy",
    "year": 2026,
    "municipality": "plovdiv",
    "kind": "funding_source",
    "funding_key": "state_subsidy",
    "display_order": 4,
    "category": "other",
    "title_bg": "Целева държавна субсидия",
    "title_en": "State targeted subsidy",
    "amount_eur": 2960000,
    "currency": "EUR",
    "plain_language_bg": "Целева държавна субсидия, насочена към конкретни обекти.",
    "plain_language_en": "State targeted subsidy allocated to specific projects.",
    "source_document": {
      "title": "Под тепето — капиталова програма за 2026 г.",
      "url": "https://podtepeto.com/aktualno/obsthina-plovdiv-planira-blizo-87-mln-evro-za-kapitalovi-razhodi-prez-2026-g/",
      "accessed_at": "2026-06-14"
    },
    "data_quality": "provisional",
    "title_de": "Staatliche gezielte Subvention",
    "title_fr": "Subvention ciblée de l'État",
    "title_it": "Sovvenzione statale mirata",
    "title_tr": "Devlet hedefli sübvansiyon",
    "title_es": "Subsidio estatal específico",
    "plain_language_de": "Staatliche gezielte Förderung für bestimmte Projekte.",
    "plain_language_fr": "Subvention ciblée de l’État allouée à des projets spécifiques.",
    "plain_language_it": "Sovvenzioni statali mirate assegnate a progetti specifici.",
    "plain_language_tr": "Belirli projelere tahsis edilen devlet hedefli sübvansiyon.",
    "plain_language_es": "Subvención estatal específica asignada a proyectos específicos."
  }
]
